<<<<<<< HEAD
var deandome = {
"type": "FeatureCollection",
"crs": { "type": "name", "properties": { "name": "urn:ogc:def:crs:OGC:1.3:CRS84" } },
"features": [
{ "type": "Feature", "properties": { "id": 1, "descrip": "unc well" }, "geometry": { "type": "Point", "coordinates": [ -79.0437431, 35.8995637 ] } }
]
}
=======
var deandome = {
"type": "FeatureCollection",
"crs": { "type": "name", "properties": { "name": "urn:ogc:def:crs:OGC:1.3:CRS84" } },
"features": [
{ "type": "Feature", "properties": { "id": 1, "descrip": "unc well" }, "geometry": { "type": "Point", "coordinates": [ -79.0437431, 35.8995637 ] } }
]
}
>>>>>>> 932bc114d3455a72b4659e97bde4983d9b2e67f6
